identibench/__init__.py
identibench/_modidx.py
identibench/benchmark.py
identibench/metrics.py
identibench/utils.py
identibench/datasets/__init__.py
identibench/datasets/broad.py
identibench/datasets/industrial_robot.py
identibench/datasets/quad_pelican.py
identibench/datasets/quad_pi.py
identibench/datasets/ship.py
identibench/datasets/workshop.py
identibench-0.1.5.dist-info/licenses/LICENSE
identibench-0.1.5.dist-info/METADATA
identibench-0.1.5.dist-info/WHEEL
identibench-0.1.5.dist-info/entry_points.txt
identibench-0.1.5.dist-info/top_level.txt
identibench-0.1.5.dist-info/RECORD
