Metadata-Version: 2.4
Name: identibench
Version: 0.1.5
Summary: Downloads and prepares various system identification benchmark datasets
Home-page: https://github.com/daniel-om-weber/identibench
Author: Daniel Oliver Martin Weber
Author-email: daniel.om.weber@gmail.com
License: Apache Software License 2.0
Keywords: nbdev jupyter notebook python
Classifier: Development Status :: 4 - Beta
Classifier: Intended Audience :: Developers
Classifier: Natural Language :: English
Classifier: Programming Language :: Python :: 3.9
Classifier: Programming Language :: Python :: 3.10
Classifier: Programming Language :: Python :: 3.11
Classifier: Programming Language :: Python :: 3.12
Classifier: Programming Language :: Python :: 3.13
Classifier: License :: OSI Approved :: Apache Software License
Requires-Python: >=3.9
License-File: LICENSE
Requires-Dist: nonlinear-benchmarks
Requires-Dist: h5py
Requires-Dist: easyDataverse>=0.4.4
Requires-Dist: pandas
Requires-Dist: gdown
Requires-Dist: bagpy
Provides-Extra: dev
Requires-Dist: matplotlib; extra == "dev"
Requires-Dist: nbdev; extra == "dev"
Requires-Dist: ipykernel; extra == "dev"
Requires-Dist: sysidentpy; extra == "dev"
Requires-Dist: twine; extra == "dev"
Dynamic: author
Dynamic: author-email
Dynamic: classifier
Dynamic: description
Dynamic: description-content-type
Dynamic: home-page
Dynamic: keywords
Dynamic: license
Dynamic: license-file
Dynamic: provides-extra
Dynamic: requires-dist
Dynamic: requires-python
Dynamic: summary
